awscli_mfa_token_manager/__init__.py
awscli_mfa_token_manager/credentials_manager.py
awscli_mfa_token_manager/token_data_builder.py
awscli_mfa_token_manager-1.0.1.data/scripts/manage_credentials
awscli_mfa_token_manager-1.0.1.dist-info/LICENSE
awscli_mfa_token_manager-1.0.1.dist-info/METADATA
awscli_mfa_token_manager-1.0.1.dist-info/WHEEL
awscli_mfa_token_manager-1.0.1.dist-info/top_level.txt
awscli_mfa_token_manager-1.0.1.dist-info/RECORD
