Metadata-Version: 2.1
Name: awscli-mfa-token-manager
Version: 1.0.1
Summary: Module to generate credentials from MFA device for AWS CLI 
Home-page: https://github.com/anadimisra/awscli_mfa_token_manager
Author: Anadi Misra
Author-email: anadi.msr@gmail.com
License: UNKNOWN
Keywords: awscli aws-sts
Platform: UNKNOWN
Classifier: Programming Language :: Python :: 3
Classifier: License :: OSI Approved :: GNU General Public License v3 or later (GPLv3+)
Classifier: Operating System :: OS Independent
Requires-Python: >=3.6.8
Requires-Dist: boto3 (==1.16.12)
